aider_install/__init__.py
aider_install/main.py
aider_install-0.1.2.dist-info/LICENSE.txt
aider_install-0.1.2.dist-info/METADATA
aider_install-0.1.2.dist-info/WHEEL
aider_install-0.1.2.dist-info/entry_points.txt
aider_install-0.1.2.dist-info/top_level.txt
aider_install-0.1.2.dist-info/RECORD
