Metadata-Version: 2.1
Name: aider-install
Version: 0.1.2
Summary: Installer for the aider AI pair programming CLI tool.
Home-page: https://github.com/Aider-AI/aider-install
Author: Paul Gauthier
Author-email: paul@aider.chat
Classifier: Programming Language :: Python :: 3
Classifier: License :: OSI Approved :: MIT License
Classifier: Operating System :: OS Independent
Requires-Python: >=3.8
License-File: LICENSE.txt
Requires-Dist: uv>=0.5.0
